pandas_to_snowflake/__init__.py
pandas_to_snowflake/pandas_to_snowflake.py
pandas_to_snowflake-2.0.1.dist-info/LICENSE.txt
pandas_to_snowflake-2.0.1.dist-info/METADATA
pandas_to_snowflake-2.0.1.dist-info/WHEEL
pandas_to_snowflake-2.0.1.dist-info/top_level.txt
pandas_to_snowflake-2.0.1.dist-info/RECORD
