Metadata-Version: 2.1
Name: pandas-to-snowflake
Version: 2.0.1
Summary: Bulk loading pandas dataframe to snowflake table
Home-page: https://github.com/nit567esh/pandas_to_snowflake
Author: Nitesh Kumar
Author-email: nit567esh@gmail.com
License: UNKNOWN
Platform: UNKNOWN
Requires-Dist: pandas
